JudgeInterface/__init__.py
JudgeInterface/abstract.py
JudgeInterface/languages.py
JudgeInterface/problems.py
JudgeInterface/submissions.py
JudgeInterface/users.py
JudgeInterface/lib/__init__.py
JudgeInterface/lib/db.py
JudgeInterface/lib/placeholder.py
JudgeInterface-1.0.9.dist-info/LICENSE
JudgeInterface-1.0.9.dist-info/METADATA
JudgeInterface-1.0.9.dist-info/WHEEL
JudgeInterface-1.0.9.dist-info/top_level.txt
JudgeInterface-1.0.9.dist-info/RECORD
