Metadata-Version: 2.1
Name: JudgeInterface
Version: 1.0.9
Summary: A DB Interface for Judge
Home-page: https://github.com/mansukim1125/JudgeInterface
Author: mansu kim
Author-email: mansukim1125@gmail.com
License: MIT
Platform: UNKNOWN
Requires-Python: >=3
License-File: LICENSE
